uatu/__init__.py
uatu/allowlist.py
uatu/audit.py
uatu/audit_cli.py
uatu/capabilities.py
uatu/chat.py
uatu/cli.py
uatu/config.py
uatu/exceptions.py
uatu/network_allowlist.py
uatu/network_security.py
uatu/permissions.py
uatu/telemetry.py
uatu/tool_hooks.py
uatu/utils.py
uatu/agents/__init__.py
uatu/chat_session/__init__.py
uatu/chat_session/commands.py
uatu/chat_session/components.py
uatu/chat_session/handlers.py
uatu/chat_session/session.py
uatu/chat_session/stats.py
uatu/tools/__init__.py
uatu/tools/base.py
uatu/tools/command_tools.py
uatu/tools/constants.py
uatu/tools/macos_tools.py
uatu/tools/proc_tools.py
uatu/tools/processes.py
uatu/tools/safe_mcp.py
uatu/tools/sdk_tools.py
uatu/ui/__init__.py
uatu/ui/approval.py
uatu/ui/completer.py
uatu/ui/console.py
uatu/ui/markdown.py
uatu/ui/output.py
uatu/ui/tool_preview.py
uatu-0.1.15.dist-info/METADATA
uatu-0.1.15.dist-info/WHEEL
uatu-0.1.15.dist-info/entry_points.txt
uatu-0.1.15.dist-info/licenses/LICENSE
uatu-0.1.15.dist-info/RECORD
