Metadata-Version: 2.4
Name: uatu
Version: 0.1.15
Summary: The Watcher - An agentic system troubleshooting tool powered by Claude
Project-URL: Homepage, https://github.com/fractalops/uatu
Project-URL: Repository, https://github.com/fractalops/uatu
Project-URL: Issues, https://github.com/fractalops/uatu/issues
Project-URL: Documentation, https://github.com/fractalops/uatu#readme
Author-email: fractalops <jstbillz@gmail.com>
License: MIT
License-File: LICENSE
Keywords: ai,claude,devops,monitoring,observability,system-administration,troubleshooting
Classifier: Development Status :: 4 - Beta
Classifier: Environment :: Console
Classifier: Intended Audience :: Developers
Classifier: Intended Audience :: System Administrators
Classifier: License :: OSI Approved :: MIT License
Classifier: Operating System :: MacOS
Classifier: Operating System :: POSIX :: Linux
Classifier: Programming Language :: Python :: 3
Classifier: Programming Language :: Python :: 3.11
Classifier: Programming Language :: Python :: 3.12
Classifier: Topic :: System :: Monitoring
Classifier: Topic :: System :: Systems Administration
Requires-Python: >=3.10
Requires-Dist: anthropic>=0.39.0
Requires-Dist: claude-agent-sdk>=0.1.6
Requires-Dist: prompt-toolkit>=3.0.0
Requires-Dist: psutil>=5.9.0
Requires-Dist: pydantic-settings>=2.0.0
Requires-Dist: pydantic>=2.0.0
Requires-Dist: rich>=13.0.0
Requires-Dist: typer>=0.12.0
Provides-Extra: dev
Requires-Dist: mypy>=1.11.0; extra == 'dev'
Requires-Dist: pytest-asyncio>=0.23.0; extra == 'dev'
Requires-Dist: pytest>=8.0.0; extra == 'dev'
Requires-Dist: ruff>=0.6.0; extra == 'dev'
